caronte/__init__.py
caronte/__main__.py
caronte/database/__init__.py
caronte/database/db.py
caronte/database/models.py
caronte/utils.py
caronte-1.0.0.dist-info/LICENSE
caronte-1.0.0.dist-info/WHEEL
caronte-1.0.0.dist-info/METADATA
caronte-1.0.0.dist-info/RECORD
